perlsub/__init__.py
perlsub/perlsub.py
perlsub/wrapper_template.pl
perlsub-0.0.2.dist-info/LICENSE
perlsub-0.0.2.dist-info/METADATA
perlsub-0.0.2.dist-info/WHEEL
perlsub-0.0.2.dist-info/top_level.txt
perlsub-0.0.2.dist-info/RECORD
