Metadata-Version: 2.1
Name: perlsub
Version: 0.0.2
Summary: A Python wrapper for Perl subroutines
Home-page: https://github.com/amad00r/perl-subroutine-wrapper
Author: amado0r (Amadeu Moya Sardà)
Author-email: <amadeumosar@gmail.com>
License: MIT
Keywords: python,perl,wrapper
Platform: UNKNOWN
Classifier: Intended Audience :: Developers
Classifier: Programming Language :: Python :: 3
License-File: LICENSE
Requires-Dist: jinja2
